big_sleep/__init__.py
big_sleep/big_sleep.py
big_sleep/biggan.py
big_sleep/cli.py
big_sleep/clip.py
big_sleep/ema.py
big_sleep/resample.py
big_sleep/version.py
big_sleep/data/bpe_simple_vocab_16e6.txt
big_sleep-0.9.1.dist-info/LICENSE
big_sleep-0.9.1.dist-info/METADATA
big_sleep-0.9.1.dist-info/WHEEL
big_sleep-0.9.1.dist-info/entry_points.txt
big_sleep-0.9.1.dist-info/top_level.txt
big_sleep-0.9.1.dist-info/RECORD
